Workbook

Sheet Counts
A1: Japan: number of applicable corporate income tax rates, fiscal years beginning 2014-2026
A2: Tokyo 23 wards, ordinary corporations (class 1 business), enterprise tax income base only. Input for the ITCI corporate_alt_minimum variable.
A4: Regime | B4: Fiscal years beginning | C4: A: rates in the PwC rate table | D4: B: full statutory schedule | E4: of which: core (= A) | F4: of which: added by the multi-prefecture rule | G4: of which: added by the 19% excluded-enterprise band | H4: Change in A vs previous regime
A5: 2014a | B5: FY beg. 1 Apr 2014 - 30 Sep 2014 | C5: =SUMIFS(Grid!$R$2:$R$189,Grid!$A$2:$A$189,$A5) -> 9 | D5: =SUMIFS(Grid!$S$2:$S$189,Grid!$A$2:$A$189,$A5) -> 11 | E5: =SUMIFS(Grid!$S$2:$S$189,Grid!$A$2:$A$189,$A5,Grid!$D$2:$D$189,"core (Convention A)") -> 9 | F5: =SUMIFS(Grid!$S$2:$S$189,Grid!$A$2:$A$189,$A5,Grid!$D$2:$D$189,"multi-prefecture") -> 2 | G5: =SUMIFS(Grid!$S$2:$S$189,Grid!$A$2:$A$189,$A5,Grid!$D$2:$D$189,"excluded enterprise (19%)") -> 0 | H5: baseline
A6: 2014b | B6: FY beg. 1 Oct 2014 - 31 Mar 2015 | C6: =SUMIFS(Grid!$R$2:$R$189,Grid!$A$2:$A$189,$A6) -> 9 | D6: =SUMIFS(Grid!$S$2:$S$189,Grid!$A$2:$A$189,$A6) -> 11 | E6: =SUMIFS(Grid!$S$2:$S$189,Grid!$A$2:$A$189,$A6,Grid!$D$2:$D$189,"core (Convention A)") -> 9 | F6: =SUMIFS(Grid!$S$2:$S$189,Grid!$A$2:$A$189,$A6,Grid!$D$2:$D$189,"multi-prefecture") -> 2 | G6: =SUMIFS(Grid!$S$2:$S$189,Grid!$A$2:$A$189,$A6,Grid!$D$2:$D$189,"excluded enterprise (19%)") -> 0 | H6: no change (about one third of the special local corporate tax returned to enterprise tax rates)
A7: 2015 | B7: FY beg. 1 Apr 2015 - 31 Mar 2016 | C7: =SUMIFS(Grid!$R$2:$R$189,Grid!$A$2:$A$189,$A7) -> 9 | D7: =SUMIFS(Grid!$S$2:$S$189,Grid!$A$2:$A$189,$A7) -> 11 | E7: =SUMIFS(Grid!$S$2:$S$189,Grid!$A$2:$A$189,$A7,Grid!$D$2:$D$189,"core (Convention A)") -> 9 | F7: =SUMIFS(Grid!$S$2:$S$189,Grid!$A$2:$A$189,$A7,Grid!$D$2:$D$189,"multi-prefecture") -> 2 | G7: =SUMIFS(Grid!$S$2:$S$189,Grid!$A$2:$A$189,$A7,Grid!$D$2:$D$189,"excluded enterprise (19%)") -> 0 | H7: no change (national rate 25.5 -> 23.9; size-based taxation expanded)
A8: 2016 | B8: FY beg. 1 Apr 2016 - 31 Mar 2017 | C8: =SUMIFS(Grid!$R$2:$R$189,Grid!$A$2:$A$189,$A8) -> 9 | D8: =SUMIFS(Grid!$S$2:$S$189,Grid!$A$2:$A$189,$A8) -> 11 | E8: =SUMIFS(Grid!$S$2:$S$189,Grid!$A$2:$A$189,$A8,Grid!$D$2:$D$189,"core (Convention A)") -> 9 | F8: =SUMIFS(Grid!$S$2:$S$189,Grid!$A$2:$A$189,$A8,Grid!$D$2:$D$189,"multi-prefecture") -> 2 | G8: =SUMIFS(Grid!$S$2:$S$189,Grid!$A$2:$A$189,$A8,Grid!$D$2:$D$189,"excluded enterprise (19%)") -> 0 | H8: no change (national rate 23.9 -> 23.4; size-based expansion phase 2)
A9: 2017 | B9: FY beg. 1 Apr 2017 - 31 Mar 2018 | C9: =SUMIFS(Grid!$R$2:$R$189,Grid!$A$2:$A$189,$A9) -> 9 | D9: =SUMIFS(Grid!$S$2:$S$189,Grid!$A$2:$A$189,$A9) -> 11 | E9: =SUMIFS(Grid!$S$2:$S$189,Grid!$A$2:$A$189,$A9,Grid!$D$2:$D$189,"core (Convention A)") -> 9 | F9: =SUMIFS(Grid!$S$2:$S$189,Grid!$A$2:$A$189,$A9,Grid!$D$2:$D$189,"multi-prefecture") -> 2 | G9: =SUMIFS(Grid!$S$2:$S$189,Grid!$A$2:$A$189,$A9,Grid!$D$2:$D$189,"excluded enterprise (19%)") -> 0 | H9: no change
A10: 2018 | B10: FY beg. 1 Apr 2018 - 31 Mar 2019 | C10: =SUMIFS(Grid!$R$2:$R$189,Grid!$A$2:$A$189,$A10) -> 9 | D10: =SUMIFS(Grid!$S$2:$S$189,Grid!$A$2:$A$189,$A10) -> 11 | E10: =SUMIFS(Grid!$S$2:$S$189,Grid!$A$2:$A$189,$A10,Grid!$D$2:$D$189,"core (Convention A)") -> 9 | F10: =SUMIFS(Grid!$S$2:$S$189,Grid!$A$2:$A$189,$A10,Grid!$D$2:$D$189,"multi-prefecture") -> 2 | G10: =SUMIFS(Grid!$S$2:$S$189,Grid!$A$2:$A$189,$A10,Grid!$D$2:$D$189,"excluded enterprise (19%)") -> 0 | H10: no change (national rate 23.4 -> 23.2)
A11: 2019a | B11: FY beg. 1 Apr 2019 - 30 Sep 2019 | C11: =SUMIFS(Grid!$R$2:$R$189,Grid!$A$2:$A$189,$A11) -> 9 | D11: =SUMIFS(Grid!$S$2:$S$189,Grid!$A$2:$A$189,$A11) -> 14 | E11: =SUMIFS(Grid!$S$2:$S$189,Grid!$A$2:$A$189,$A11,Grid!$D$2:$D$189,"core (Convention A)") -> 9 | F11: =SUMIFS(Grid!$S$2:$S$189,Grid!$A$2:$A$189,$A11,Grid!$D$2:$D$189,"multi-prefecture") -> 2 | G11: =SUMIFS(Grid!$S$2:$S$189,Grid!$A$2:$A$189,$A11,Grid!$D$2:$D$189,"excluded enterprise (19%)") -> 3 | H11: no change in A. B rises 11 -> 14: the 19% statutory rate revives for excluded enterprises
A12: 2019b | B12: FY beg. 1 Oct 2019 - 31 Mar 2020 | C12: =SUMIFS(Grid!$R$2:$R$189,Grid!$A$2:$A$189,$A12) -> 9 | D12: =SUMIFS(Grid!$S$2:$S$189,Grid!$A$2:$A$189,$A12) -> 14 | E12: =SUMIFS(Grid!$S$2:$S$189,Grid!$A$2:$A$189,$A12,Grid!$D$2:$D$189,"core (Convention A)") -> 9 | F12: =SUMIFS(Grid!$S$2:$S$189,Grid!$A$2:$A$189,$A12,Grid!$D$2:$D$189,"multi-prefecture") -> 2 | G12: =SUMIFS(Grid!$S$2:$S$189,Grid!$A$2:$A$189,$A12,Grid!$D$2:$D$189,"excluded enterprise (19%)") -> 3 | H12: no change (special local corporate tax replaced by the special corporate business tax; local corporate tax 4.4 -> 10.3)
A13: 2020 | B13: FY beg. 1 Apr 2020 - 31 Mar 2021 | C13: =SUMIFS(Grid!$R$2:$R$189,Grid!$A$2:$A$189,$A13) -> 9 | D13: =SUMIFS(Grid!$S$2:$S$189,Grid!$A$2:$A$189,$A13) -> 14 | E13: =SUMIFS(Grid!$S$2:$S$189,Grid!$A$2:$A$189,$A13,Grid!$D$2:$D$189,"core (Convention A)") -> 9 | F13: =SUMIFS(Grid!$S$2:$S$189,Grid!$A$2:$A$189,$A13,Grid!$D$2:$D$189,"multi-prefecture") -> 2 | G13: =SUMIFS(Grid!$S$2:$S$189,Grid!$A$2:$A$189,$A13,Grid!$D$2:$D$189,"excluded enterprise (19%)") -> 3 | H13: no change
A14: 2021 | B14: FY beg. 1 Apr 2021 - 31 Mar 2022 | C14: =SUMIFS(Grid!$R$2:$R$189,Grid!$A$2:$A$189,$A14) -> 9 | D14: =SUMIFS(Grid!$S$2:$S$189,Grid!$A$2:$A$189,$A14) -> 14 | E14: =SUMIFS(Grid!$S$2:$S$189,Grid!$A$2:$A$189,$A14,Grid!$D$2:$D$189,"core (Convention A)") -> 9 | F14: =SUMIFS(Grid!$S$2:$S$189,Grid!$A$2:$A$189,$A14,Grid!$D$2:$D$189,"multi-prefecture") -> 2 | G14: =SUMIFS(Grid!$S$2:$S$189,Grid!$A$2:$A$189,$A14,Grid!$D$2:$D$189,"excluded enterprise (19%)") -> 3 | H14: no change
A15: 2022 | B15: FY beg. 1 Apr 2022 - 31 Mar 2023 | C15: =SUMIFS(Grid!$R$2:$R$189,Grid!$A$2:$A$189,$A15) -> 7 | D15: =SUMIFS(Grid!$S$2:$S$189,Grid!$A$2:$A$189,$A15) -> 12 | E15: =SUMIFS(Grid!$S$2:$S$189,Grid!$A$2:$A$189,$A15,Grid!$D$2:$D$189,"core (Convention A)") -> 7 | F15: =SUMIFS(Grid!$S$2:$S$189,Grid!$A$2:$A$189,$A15,Grid!$D$2:$D$189,"multi-prefecture") -> 2 | G15: =SUMIFS(Grid!$S$2:$S$189,Grid!$A$2:$A$189,$A15,Grid!$D$2:$D$189,"excluded enterprise (19%)") -> 3 | H15: 9 -> 7: graduated income-base enterprise rates withdrawn for size-based taxpayers (FY2022 reform)
A16: 2023 | B16: FY beg. 1 Apr 2023 - 31 Mar 2024 | C16: =SUMIFS(Grid!$R$2:$R$189,Grid!$A$2:$A$189,$A16) -> 7 | D16: =SUMIFS(Grid!$S$2:$S$189,Grid!$A$2:$A$189,$A16) -> 12 | E16: =SUMIFS(Grid!$S$2:$S$189,Grid!$A$2:$A$189,$A16,Grid!$D$2:$D$189,"core (Convention A)") -> 7 | F16: =SUMIFS(Grid!$S$2:$S$189,Grid!$A$2:$A$189,$A16,Grid!$D$2:$D$189,"multi-prefecture") -> 2 | G16: =SUMIFS(Grid!$S$2:$S$189,Grid!$A$2:$A$189,$A16,Grid!$D$2:$D$189,"excluded enterprise (19%)") -> 3 | H16: no change
... A19: 2026 | B19: FY beg. on/after 1 Apr 2026 | C19: =SUMIFS(Grid!$R$2:$R$189,Grid!$A$2:$A$189,$A19) -> 9 | D19: =SUMIFS(Grid!$S$2:$S$189,Grid!$A$2:$A$189,$A19) -> 15 | E19: =SUMIFS(Grid!$S$2:$S$189,Grid!$A$2:$A$189,$A19,Grid!$D$2:$D$189,"core (Convention A)") -> 9 | F19: =SUMIFS(Grid!$S$2:$S$189,Grid!$A$2:$A$189,$A19,Grid!$D$2:$D$189,"multi-prefecture") -> 3 | G19: =SUMIFS(Grid!$S$2:$S$189,Grid!$A$2:$A$189,$A19,Grid!$D$2:$D$189,"excluded enterprise (19%)") -> 3 | H19: no change (4% defence surtax applies to all cells proportionally)
B20: Check: columns E+F+G equal column D | C20: =SUM(C5:C19) -> 129 | D20: =SUM(D5:D19) -> 188 | E20: =SUM(E5:E19) -> 129 | F20: =SUM(F5:F19) -> 32 | G20: =SUM(G5:G19) -> 27

Sheet Grid
A1: Regime | B1: Fiscal years beginning | C1: Scope | D1: Classifier group | E1: Paid-in capital | F1: Income bracket (enterprise tax) | G1: Enterprise rate applied | H1: National rate variant | I1: National CIT rate (%) | J1: Enterprise tax, income base (%) | K1: Standard income-base rate (base of SBT) (%) | L1: Special local corp. tax / special corp. business tax (% of income base) | M1: Local corporate tax (% of CIT) | N1: Inhabitants' tax, super (% of CIT) | O1: Defence surtax (% of CIT) | P1: Combined marginal statutory rate (%) | Q1: Effective statutory rate (%) | R1: New rate under A | S1: New rate under B | T1: Note
A2: 2014a | B2: FY beg. 1 Apr 2014 - 30 Sep 2014 | C2: A | D2: core (Convention A) | E2: <= JPY 100m | F2: <= JPY 4m | G2: standard | H2: 15 (Sp.Meas. 42-3-2) | I2: 15 | J2: 2.7 | K2: 2.7 | L2: 81 | M2: 0 | N2: 20.7 | O2: 0 | P2: =I2*(1+M2/100+N2/100+O2/100)+J2+L2/100*K2 -> 22.992 | Q2: =P2/(1+J2/100+L2/100*K2/100) -> 21.920734 | R2: 1 | S2: 1 | T2: graduated brackets, standard enterprise rate (income <= JPY 25m and revenue <= JPY 200m)
A3: 2014a | B3: FY beg. 1 Apr 2014 - 30 Sep 2014 | C3: A | D3: core (Convention A) | E3: <= JPY 100m | F3: <= JPY 4m | G3: Tokyo super | H3: 15 (Sp.Meas. 42-3-2) | I3: 15 | J3: 2.95 | K3: 2.7 | L3: 81 | M3: 0 | N3: 20.7 | O3: 0 | P3: =I3*(1+M3/100+N3/100+O3/100)+J3+L3/100*K3 -> 23.242 | Q3: =P3/(1+J3/100+L3/100*K3/100) -> 22.106395 | R3: 1 | S3: 1 | T3: graduated brackets, Tokyo super rate (income > JPY 25m or revenue > JPY 200m)
A4: 2014a | B4: FY beg. 1 Apr 2014 - 30 Sep 2014 | C4: A | D4: core (Convention A) | E4: <= JPY 100m | F4: JPY 4-8m | G4: standard | H4: 15 (Sp.Meas. 42-3-2) | I4: 15 | J4: 4 | K4: 4 | L4: 81 | M4: 0 | N4: 20.7 | O4: 0 | P4: =I4*(1+M4/100+N4/100+O4/100)+J4+L4/100*K4 -> 25.345 | Q4: =P4/(1+J4/100+L4/100*K4/100) -> 23.633905 | R4: 1 | S4: 1 | T4: graduated brackets, standard enterprise rate (income <= JPY 25m and revenue <= JPY 200m)
A5: 2014a | B5: FY beg. 1 Apr 2014 - 30 Sep 2014 | C5: A | D5: core (Convention A) | E5: <= JPY 100m | F5: JPY 4-8m | G5: Tokyo super | H5: 15 (Sp.Meas. 42-3-2) | I5: 15 | J5: 4.365 | K5: 4 | L5: 81 | M5: 0 | N5: 20.7 | O5: 0 | P5: =I5*(1+M5/100+N5/100+O5/100)+J5+L5/100*K5 -> 25.71 | Q5: =P5/(1+J5/100+L5/100*K5/100) -> 23.892942 | R5: 1 | S5: 1 | T5: graduated brackets, Tokyo super rate (income > JPY 25m or revenue > JPY 200m)
A6: 2014a | B6: FY beg. 1 Apr 2014 - 30 Sep 2014 | C6: A | D6: core (Convention A) | E6: <= JPY 100m | F6: > JPY 8m | G6: standard | H6: general | I6: 25.5 | J6: 5.3 | K6: 5.3 | L6: 81 | M6: 0 | N6: 20.7 | O6: 0 | P6: =I6*(1+M6/100+N6/100+O6/100)+J6+L6/100*K6 -> 40.3715 | Q6: =P6/(1+J6/100+L6/100*K6/100) -> 36.837663 | R6: 1 | S6: 1 | T6: graduated brackets, standard enterprise rate (income <= JPY 25m and revenue <= JPY 200m)
A7: 2014a | B7: FY beg. 1 Apr 2014 - 30 Sep 2014 | C7: A | D7: core (Convention A) | E7: <= JPY 100m | F7: > JPY 8m | G7: Tokyo super | H7: general | I7: 25.5 | J7: 5.78 | K7: 5.3 | L7: 81 | M7: 0 | N7: 20.7 | O7: 0 | P7: =I7*(1+M7/100+N7/100+O7/100)+J7+L7/100*K7 -> 40.8515 | Q7: =P7/(1+J7/100+L7/100*K7/100) -> 37.113098 | R7: 1 | S7: 1 | T7: graduated brackets, Tokyo super rate (income > JPY 25m or revenue > JPY 200m)
A8: 2014a | B8: FY beg. 1 Apr 2014 - 30 Sep 2014 | C8: A | D8: core (Convention A) | E8: > JPY 100m | F8: <= JPY 4m | G8: Tokyo super | H8: general | I8: 25.5 | J8: 1.69 | K8: 1.5 | L8: 148 | M8: 0 | N8: 20.7 | O8: 0 | P8: =I8*(1+M8/100+N8/100+O8/100)+J8+L8/100*K8 -> 34.6885 | Q8: =P8/(1+J8/100+L8/100*K8/100) -> 33.383216 | R8: 1 | S8: 1 | T8: size-based taxpayer, graduated income base
A9: 2014a | B9: FY beg. 1 Apr 2014 - 30 Sep 2014 | C9: A | D9: core (Convention A) | E9: > JPY 100m | F9: JPY 4-8m | G9: Tokyo super | H9: general | I9: 25.5 | J9: 2.475 | K9: 2.2 | L9: 148 | M9: 0 | N9: 20.7 | O9: 0 | P9: =I9*(1+M9/100+N9/100+O9/100)+J9+L9/100*K9 -> 36.5095 | Q9: =P9/(1+J9/100+L9/100*K9/100) -> 34.530554 | R9: 1 | S9: 1 | T9: size-based taxpayer, graduated income base
A10: 2014a | B10: FY beg. 1 Apr 2014 - 30 Sep 2014 | C10: A | D10: core (Convention A) | E10: > JPY 100m | F10: > JPY 8m | G10: Tokyo super | H10: general | I10: 25.5 | J10: 3.26 | K10: 2.9 | L10: 148 | M10: 0 | N10: 20.7 | O10: 0 | P10: =I10*(1+M10/100+N10/100+O10/100)+J10+L10/100*K10 -> 38.3305 | Q10: =P10/(1+J10/100+L10/100*K10/100) -> 35.63904 | R10: 1 | S10: 1 | T10: size-based taxpayer, graduated income base
A11: 2014a | B11: FY beg. 1 Apr 2014 - 30 Sep 2014 | C11: B | D11: multi-prefecture | E11: <= JPY 100m | F11: first JPY 8m, no graduation | G11: standard | H11: 15 | I11: 15 | J11: 5.3 | K11: 5.3 | L11: 81 | M11: 0 | N11: 20.7 | O11: 0 | P11: =I11*(1+M11/100+N11/100+O11/100)+J11+L11/100*K11 -> 27.698 | Q11: =P11/(1+J11/100+L11/100*K11/100) -> 25.273512 | R11: 0 | S11: 1 | T11: capital >= JPY 10m and offices in 3+ prefectures: graduated enterprise brackets disapplied, so the top rate applies to the first JPY 8m as well (Local Tax Act art. 72-24-7)
A12: 2014a | B12: FY beg. 1 Apr 2014 - 30 Sep 2014 | C12: B | D12: multi-prefecture | E12: <= JPY 100m | F12: first JPY 8m, no graduation | G12: Tokyo super | H12: 15 | I12: 15 | J12: 5.78 | K12: 5.3 | L12: 81 | M12: 0 | N12: 20.7 | O12: 0 | P12: =I12*(1+M12/100+N12/100+O12/100)+J12+L12/100*K12 -> 28.178 | Q12: =P12/(1+J12/100+L12/100*K12/100) -> 25.599375 | R12: 0 | S12: 1 | T12: capital >= JPY 10m and offices in 3+ prefectures: graduated enterprise brackets disapplied, so the top rate applies to the first JPY 8m as well (Local Tax Act art. 72-24-7)
A13: 2014b | B13: FY beg. 1 Oct 2014 - 31 Mar 2015 | C13: A | D13: core (Convention A) | E13: <= JPY 100m | F13: <= JPY 4m | G13: standard | H13: 15 (Sp.Meas. 42-3-2) | I13: 15 | J13: 3.4 | K13: 3.4 | L13: 43.2 | M13: 4.4 | N13: 16.3 | O13: 0 | P13: =I13*(1+M13/100+N13/100+O13/100)+J13+L13/100*K13 -> 22.9738 | Q13: =P13/(1+J13/100+L13/100*K13/100) -> 21.907183 | R13: 1 | S13: 1 | T13: graduated brackets, standard enterprise rate (income <= JPY 25m and revenue <= JPY 200m)
... A189: 2026 | B189: FY beg. on/after 1 Apr 2026 | C189: B | D189: excluded enterprise (19%) | E189: <= JPY 100m | F189: JPY 4-8m | G189: Tokyo super | H189: 19 | I189: 19 | J189: 5.665 | K189: 5.3 | L189: 37 | M189: 10.3 | N189: 10.4 | O189: 4 | P189: =I189*(1+M189/100+N189/100+O189/100)+J189+L189/100*K189 -> 31.319 | Q189: =P189/(1+J189/100+L189/100*K189/100) -> 29.099846 | R189: 0 | S189: 1 | T189: excluded enterprise (3-yr average income > JPY 1.5bn): statutory 19% under Corp. Tax Act art. 66(2)

Sheet Parameters
A1: Regime | B1: Fiscal years beginning | C1: National CIT rate, general (%) | D1: Rates available on the first JPY 8m (%) | E1: Enterprise tax income base, capital <= JPY 100m: standard (%) | F1: ... Tokyo super (%) | G1: Enterprise tax income base, capital > JPY 100m: standard (%) | H1: ... Tokyo super (%) | I1: Special local corp. tax / special corp. business tax, non-size-based (%) | J1: ... size-based (%) | K1: Local corporate tax (% of CIT) | L1: Inhabitants' tax, 23 wards: standard (%) | M1: ... super (%) | N1: Special defence corporate surtax (% of CIT) | O1: Graduated income base for size-based taxpayers?
A2: 2014a | B2: FY beg. 1 Apr 2014 - 30 Sep 2014 | C2: 25.5 | D2: 15 | E2: 2.7 / 4 / 5.3 | F2: 2.95 / 4.365 / 5.78 | G2: 1.5 / 2.2 / 2.9 | H2: 1.69 / 2.475 / 3.26 | I2: 81 | J2: 148 | K2: 0 | L2: 17.3 | M2: 20.7 | N2: 0 | O2: yes
A3: 2014b | B3: FY beg. 1 Oct 2014 - 31 Mar 2015 | C3: 25.5 | D3: 15 | E3: 3.4 / 5.1 / 6.7 | F3: 3.65 / 5.465 / 7.18 | G3: 2.2 / 3.2 / 4.3 | H3: 2.39 / 3.475 / 4.66 | I3: 43.2 | J3: 67.4 | K3: 4.4 | L3: 12.9 | M3: 16.3 | N3: 0 | O3: yes
A4: 2015 | B4: FY beg. 1 Apr 2015 - 31 Mar 2016 | C4: 23.9 | D4: 15 | E4: 3.4 / 5.1 / 6.7 | F4: 3.65 / 5.465 / 7.18 | G4: 1.6 / 2.3 / 3.1 | H4: 1.755 / 2.53 / 3.4 | I4: 43.2 | J4: 93.5 | K4: 4.4 | L4: 12.9 | M4: 16.3 | N4: 0 | O4: yes
A5: 2016 | B5: FY beg. 1 Apr 2016 - 31 Mar 2017 | C5: 23.4 | D5: 15 | E5: 3.4 / 5.1 / 6.7 | F5: 3.65 / 5.465 / 7.18 | G5: 0.3 / 0.5 / 0.7 | H5: 0.395 / 0.635 / 0.88 | I5: 43.2 | J5: 414.2 | K5: 4.4 | L5: 12.9 | M5: 16.3 | N5: 0 | O5: yes
A6: 2017 | B6: FY beg. 1 Apr 2017 - 31 Mar 2018 | C6: 23.4 | D6: 15 | E6: 3.4 / 5.1 / 6.7 | F6: 3.65 / 5.465 / 7.18 | G6: 0.3 / 0.5 / 0.7 | H6: 0.395 / 0.635 / 0.88 | I6: 43.2 | J6: 414.2 | K6: 4.4 | L6: 12.9 | M6: 16.3 | N6: 0 | O6: yes
A7: 2018 | B7: FY beg. 1 Apr 2018 - 31 Mar 2019 | C7: 23.2 | D7: 15 | E7: 3.4 / 5.1 / 6.7 | F7: 3.65 / 5.465 / 7.18 | G7: 0.3 / 0.5 / 0.7 | H7: 0.395 / 0.635 / 0.88 | I7: 43.2 | J7: 414.2 | K7: 4.4 | L7: 12.9 | M7: 16.3 | N7: 0 | O7: yes
A8: 2019a | B8: FY beg. 1 Apr 2019 - 30 Sep 2019 | C8: 23.2 | D8: 15 / 19 | E8: 3.4 / 5.1 / 6.7 | F8: 3.65 / 5.465 / 7.18 | G8: 0.3 / 0.5 / 0.7 | H8: 0.395 / 0.635 / 0.88 | I8: 43.2 | J8: 414.2 | K8: 4.4 | L8: 12.9 | M8: 16.3 | N8: 0 | O8: yes
A9: 2019b | B9: FY beg. 1 Oct 2019 - 31 Mar 2020 | C9: 23.2 | D9: 15 / 19 | E9: 3.5 / 5.3 / 7 | F9: 3.75 / 5.665 / 7.48 | G9: 0.4 / 0.7 / 1 | H9: 0.495 / 0.835 / 1.18 | I9: 37 | J9: 260 | K9: 10.3 | L9: 7 | M9: 10.4 | N9: 0 | O9: yes
A10: 2020 | B10: FY beg. 1 Apr 2020 - 31 Mar 2021 | C10: 23.2 | D10: 15 / 19 | E10: 3.5 / 5.3 / 7 | F10: 3.75 / 5.665 / 7.48 | G10: 0.4 / 0.7 / 1 | H10: 0.495 / 0.835 / 1.18 | I10: 37 | J10: 260 | K10: 10.3 | L10: 7 | M10: 10.4 | N10: 0 | O10: yes
A11: 2021 | B11: FY beg. 1 Apr 2021 - 31 Mar 2022 | C11: 23.2 | D11: 15 / 19 | E11: 3.5 / 5.3 / 7 | F11: 3.75 / 5.665 / 7.48 | G11: 0.4 / 0.7 / 1 | H11: 0.495 / 0.835 / 1.18 | I11: 37 | J11: 260 | K11: 10.3 | L11: 7 | M11: 10.4 | N11: 0 | O11: yes
A12: 2022 | B12: FY beg. 1 Apr 2022 - 31 Mar 2023 | C12: 23.2 | D12: 15 / 19 | E12: 3.5 / 5.3 / 7 | F12: 3.75 / 5.665 / 7.48 | G12: 1 | H12: 1.18 | I12: 37 | J12: 260 | K12: 10.3 | L12: 7 | M12: 10.4 | N12: 0 | O12: no
A13: 2023 | B13: FY beg. 1 Apr 2023 - 31 Mar 2024 | C13: 23.2 | D13: 15 / 19 | E13: 3.5 / 5.3 / 7 | F13: 3.75 / 5.665 / 7.48 | G13: 1 | H13: 1.18 | I13: 37 | J13: 260 | K13: 10.3 | L13: 7 | M13: 10.4 | N13: 0 | O13: no
... A16: 2026 | B16: FY beg. on/after 1 Apr 2026 | C16: 23.2 | D16: 15 / 17 / 19 | E16: 3.5 / 5.3 / 7 | F16: 3.75 / 5.665 / 7.48 | G16: 1 | H16: 1.18 | I16: 37 | J16: 260 | K16: 10.3 | L16: 7 | M16: 10.4 | N16: 4 | O16: no
A18: Only the super column of inhabitants' tax feeds the Grid, following the PwC presentation. The standard rate is shown for reference; it applies where capital <= JPY 100m and corporate tax <= JPY 10m.
A20: Sources
A21: National rates 25.5 / 23.9 / 23.4 / 23.2 and the SME special rate (15%, raised to 17% where income > JPY 1bn from FY2025): Corporation Tax Act art. 66(1)-(2); Act on Special Measures Concerning Taxation art. 42-3-2(1); MOF, Hojinzei no zeiritsu no suii, https://www.mof.go.jp/tax_policy/summary/corporation/082.pdf
A22: Excluded enterprise (tekiyo jogai jigyosha), 3-year average income > JPY 1.5bn, FY beginning on/after 1 Apr 2019: Act on Special Measures Concerning Taxation art. 42-4(19)(viii) (cited as art. 42-4(8)(viii) in earlier NTA guidance); Order art. 27-4(13)-(17); NTA, https://www.nta.go.jp/law/joho-zeikaishaku/hojin/group_faq/83.htm
A23: Enterprise tax and inhabitants tax rates by period, Tokyo: Tokyo Metropolitan Bureau of Taxation, https://www.tax.metro.tokyo.lg.jp/kazei/work/houjinji and the FY2014 rate-revision leaflet, https://www.tax.metro.tokyo.lg.jp/documents/d/tax/zeiritu_kaisei ; Local Tax Act art. 72-24-7
A24: Graduated income-base rates withdrawn for size-based taxpayers, FY beginning on/after 1 Apr 2022: FY2022 (Reiwa 4) tax reform; Tokyo rate table note 3
A25: Special defence corporate surtax, 4% of corporate tax less a JPY 5m basic deduction, FY beginning on/after 1 Apr 2026: 2025 Tax Reform Act
A26: Tokyo super-rate trigger for enterprise tax: annual income > JPY 25m or annual revenue > JPY 200m. Graduated brackets disapplied where capital >= JPY 10m and offices in 3 or more prefectures

Sheet Notes
A1: Method, scope and coding notes
A3: Counting rule
A4: A combination is counted where it produces a distinct pair of (national CIT marginal rate, Tokyo enterprise tax income-base marginal rate). Deduplication makes no difference in any year: every admitted income-revenue-capital combination generates a distinct rate, so the count of unique rates equals the count of bracket cells throughout FY2014-FY2026.
A6: Scope A - rates visible in the PwC rate table
A7: Classifiers: paid-in capital (JPY 100m), the enterprise tax graduated brackets (JPY 4m / JPY 8m), the Tokyo super-rate trigger (income > JPY 25m or revenue > JPY 200m), and the JPY 1bn income threshold for the 17% band. This is the scope that yields 9 for FY2026.
A9: Scope B - full statutory schedule
A10: A plus the two classifiers PwC relegates to footnotes. (i) Multi-prefecture rule: where capital is at least JPY 10m and the corporation has offices in three or more prefectures, the graduated enterprise brackets are disapplied, so the top rate applies to the first JPY 8m as well. This adds exactly two cells in every year, 15% + 7.0% and 15% + 7.48% at current rates, and a third from FY2025 via the 17% band. It adds nothing where capital exceeds JPY 100m. (ii) The 19% excluded-enterprise band, which adds three cells from FY2019, one of which also requires multi-prefecture status.
A12: Incidence differs sharply from cell count
A13: The 19% band requires three-year average income above JPY 1.5bn while capital stays at or below JPY 100m, a small population. The multi-prefecture rule requires only JPY 10m of capital, historically the standard minimum for a kabushiki kaisha, plus establishments in three prefectures, which is an ordinary mid-sized profile. If the variable is meant to reflect rate multiplicity taxpayers actually face, the multi-prefecture cells have the stronger claim and the 19% band the weaker one, notwithstanding that the 19% band contributes more cells. No published cross-tabulation of capital class by number of prefectures of establishment exists in the NTA Kaisha Hyohon Chosa.
A15: A duplicate that is not a duplicate
A16: A multi-prefecture corporation with income above JPY 8m faces the same marginal rate as a graduated corporation in the same bracket. That is the same cell rather than a second one, which is why the multi-prefecture rows in the Grid cover only the first JPY 8m.
A18: Outside the scope of the count
... A25: Combined marginal statutory rate = national CIT rate x (1 + local corporate tax + inhabitants' tax + defence surtax) + enterprise tax income-base rate + special local corporate tax (or special corporate business tax) x the standard-rate income-base rate for the same bracket. The effective statutory rate divides by (1 + enterprise tax + special corporate business tax) because both are deductible. FY2026 reproduces the PwC figures of 39.00 / 35.43 for capital above JPY 100m and 32.71 / 31.52 for the top SME bracket.
